malet/experiment.py
malet/plot.py
malet/utils.py
malet/plot_utils/data_processor.py
malet/plot_utils/plot_drawer.py
malet/plot_utils/utils.py
malet-0.2.1.dist-info/LICENSE
malet-0.2.1.dist-info/METADATA
malet-0.2.1.dist-info/WHEEL
malet-0.2.1.dist-info/entry_points.txt
malet-0.2.1.dist-info/top_level.txt
malet-0.2.1.dist-info/RECORD
