Metadata-Version: 2.1
Name: malet
Version: 0.2.1
Summary: Malet: a tool for machine learning experiment
Author-email: Dongyeop Lee <dylee23@postech.ac.kr>
License: Copyright (c) 2023 Dongyeop Lee
Project-URL: Repository, https://github.com/edong6768/Malet.git
Keywords: machine learning,experiment,plot
Classifier: Intended Audience :: Science/Research
Classifier: License :: OSI Approved :: MIT License
Classifier: Topic :: Scientific/Engineering :: Artificial Intelligence
Classifier: Programming Language :: Python :: 3
Classifier: Programming Language :: Python :: 3.8
Classifier: Programming Language :: Python :: 3.9
Classifier: Programming Language :: Python :: 3.10
Requires-Python: >=3.8
License-File: LICENSE
Requires-Dist: absl-py ==1.0.0
Requires-Dist: gitpython
Requires-Dist: pandas
Requires-Dist: matplotlib
Requires-Dist: ml-collections ==0.1.0
Requires-Dist: numpy
Requires-Dist: rich
Requires-Dist: seaborn
